{
  "parent": "minecraft:recipes/root",
  "criteria": {
    "has_hercules_chestplate": {
      "conditions": {
        "items": [
          {
            "items": [
              "beetlebox:hercules_chestplate"
            ]
          }
        ]
      },
      "trigger": "minecraft:inventory_changed"
    },
    "has_the_recipe": {
      "conditions": {
        "recipe": "minecraft:upgrade_hercules_chest_1"
      },
      "trigger": "minecraft:recipe_unlocked"
    }
  },
  "requirements": [
    [
      "has_hercules_chestplate",
      "has_the_recipe"
    ]
  ],
  "rewards": {
    "recipes": [
      "minecraft:upgrade_hercules_chest_1"
    ]
  }
}