{
  "parent": "minecraft:recipes/root",
  "criteria": {
    "has_the_recipe": {
      "conditions": {
        "recipe": "minecraft:upgrade_titanus_helmet_0"
      },
      "trigger": "minecraft:recipe_unlocked"
    },
    "has_titanus_helmet": {
      "conditions": {
        "items": [
          {
            "items": [
              "beetlebox:titanus_helmet"
            ]
          }
        ]
      },
      "trigger": "minecraft:inventory_changed"
    }
  },
  "requirements": [
    [
      "has_titanus_helmet",
      "has_the_recipe"
    ]
  ],
  "rewards": {
    "recipes": [
      "minecraft:upgrade_titanus_helmet_0"
    ]
  }
}